shield_badger/__init__.py
shield_badger/__main__.py
shield_badger/cli.py
shield_badger/settings.py
shield_badger/utils.py
shield_badger-0.1.0.dist-info/METADATA
shield_badger-0.1.0.dist-info/WHEEL
shield_badger-0.1.0.dist-info/entry_points.txt
shield_badger-0.1.0.dist-info/RECORD
